LICENSE
README.md
setup.py
osuclient/__init__.py
osuclient.egg-info/PKG-INFO
osuclient.egg-info/SOURCES.txt
osuclient.egg-info/dependency_links.txt
osuclient.egg-info/requires.txt
osuclient.egg-info/top_level.txt
osuclient/client/__init__.py
osuclient/client/bancho.py
osuclient/client/constants.py
osuclient/client/exceptions.py
osuclient/client/player_state.py
osuclient/packets/__init__.py
osuclient/packets/builders.py
osuclient/packets/constants.py
osuclient/packets/rw.py
osuclient/utils/__init__.py
osuclient/utils/hashes.py