Metadata-Version: 2.1
Name: osuclient
Version: 0.2.1
Summary: A simple library for programmatic interfacing with osu servers.
Home-page: https://github.com/RealistikDash/osuclient.py
License: MIT
Project-URL: GitHub: repo, https://github.com/RealistikDash/osuclient.py
Project-URL: GitHub: issues, https://github.com/RealistikDash/osuclient.py/issues
Classifier: Programming Language :: Python :: 3
Classifier: Programming Language :: Python :: 3.11
Classifier: Programming Language :: Python :: 3.10
Classifier: Programming Language :: Python :: 3.9
Classifier: Programming Language :: Python :: 3.8
Classifier: Programming Language :: Python :: 3.7
Classifier: License :: OSI Approved :: MIT License
Classifier: Development Status :: 3 - Alpha
Requires-Python: >=3.7
License-File: LICENSE
